<?xml version="1.0" encoding="utf-8"?>
<AssetBundleConfig xmlns:xsd="http://www.w3.org/2001/XMLSchema" xmlns:xsi="http://www.w3.org/2001/XMLSchema-instance">
  <ABList ABName="c0001" AssetName="C0001.prefab" Path="Assets/GameData/Prefabs/Role/C0001.prefab" Crc="2722895958">
    <ABDependce>textures</ABDependce>
    <ABDependce>shaders</ABDependce>
  </ABList>
  <ABList ABName="gamestart" AssetName="GameStart.prefab" Path="Assets/GameData/Prefabs/GameStart.prefab" Crc="661067300" />
  <ABList ABName="loadingpanel" AssetName="LoadingPanel.prefab" Path="Assets/GameData/Prefabs/UGUI/Panel/LoadingPanel.prefab" Crc="968375833" />
  <ABList ABName="menupanel" AssetName="MenuPanel.prefab" Path="Assets/GameData/Prefabs/UGUI/Panel/MenuPanel.prefab" Crc="2681775694" />
  <ABList ABName="particletest" AssetName="ParticleTest.prefab" Path="Assets/GameData/Prefabs/Effect/ParticleTest.prefab" Crc="2693189025" />
  <ABList ABName="shaders" AssetName="Hero-Battle.shader" Path="Assets/GameData/Shaders/Hero-Battle.shader" Crc="3448524930" />
  <ABList ABName="sounds" AssetName="music_battle.mp3" Path="Assets/GameData/Sounds/music_battle.mp3" Crc="3462996725" />
  <ABList ABName="textures" AssetName="TopMatcap11.png" Path="Assets/GameData/Textures/TopMatcap11.png" Crc="220477938" />
  <ABList ABName="uisprite" AssetName="image1.png" Path="Assets/GameData/UISprite/image1.png" Crc="631644006" />
  <ABList ABName="uisprite" AssetName="image2.png" Path="Assets/GameData/UISprite/image2.png" Crc="1644586422" />
</AssetBundleConfig>